MANIFEST.in
README.md
setup.py
automanpy/__init__.py
automanpy/automan.py
automanpy/test_automan.py
automanpy.egg-info/PKG-INFO
automanpy.egg-info/SOURCES.txt
automanpy.egg-info/dependency_links.txt
automanpy.egg-info/requires.txt
automanpy.egg-info/top_level.txt
automanpy/core/__init__.py
automanpy/core/automanlib.py
automanpy/core/automanlib_rpc_pb2.py
automanpy/core/automanlib_rpc_pb2_grpc.py
automanpy/core/batchjob.py
automanpy/core/outcomes.py
automanpy/core/pyautomanexceptions.py
automanpy/core/test_core.py
automanpy/core/grpc_classes/__init__.py
automanpy/core/grpc_classes/automanlib_classes_pb2.py
automanpy/core/grpc_classes/automanlib_classes_pb2_grpc.py
automanpy/core/rpc_server/__init__.py
automanpy/core/rpc_server/pack/.DS_Store
automanpy/core/rpc_server/pack/Makefile
automanpy/core/rpc_server/pack/VERSION
automanpy/core/rpc_server/pack/bin/PyAutoManRpcServer
automanpy/core/rpc_server/pack/bin/PyAutoManRpcServer.bat
automanpy/core/rpc_server/pack/lib/antlr-2.7.2.jar
automanpy/core/rpc_server/pack/lib/automan_2.11-1.2.0.jar
automanpy/core/rpc_server/pack/lib/axis-1.4.jar
automanpy/core/rpc_server/pack/lib/axis-ant-1.4.jar
automanpy/core/rpc_server/pack/lib/axis-jaxrpc-1.4.jar
automanpy/core/rpc_server/pack/lib/axis-saaj-1.4.jar
automanpy/core/rpc_server/pack/lib/axis-wsdl4j-1.5.1.jar
automanpy/core/rpc_server/pack/lib/commons-beanutils-core-1.7.0.jar
automanpy/core/rpc_server/pack/lib/commons-chain-1.1.jar
automanpy/core/rpc_server/pack/lib/commons-codec-1.4.jar
automanpy/core/rpc_server/pack/lib/commons-collections-3.2.1.jar
automanpy/core/rpc_server/pack/lib/commons-dbcp-1.2.2.jar
automanpy/core/rpc_server/pack/lib/commons-digester-1.8.jar
automanpy/core/rpc_server/pack/lib/commons-discovery-0.4.jar
automanpy/core/rpc_server/pack/lib/commons-httpclient-3.1.jar
automanpy/core/rpc_server/pack/lib/commons-jelly-tags-velocity-1.0.jar
automanpy/core/rpc_server/pack/lib/commons-lang-2.4.jar
automanpy/core/rpc_server/pack/lib/commons-logging-1.0.4.jar
automanpy/core/rpc_server/pack/lib/commons-logging-api-1.0.4.jar
automanpy/core/rpc_server/pack/lib/commons-pool-1.5.4.jar
