Metadata-Version: 2.1
Name: automanpy
Version: 0.4.2b3
Summary: Python bindings for AutoMan Runtime. Software is current in development, and not properly tested.
Home-page: https://github.com/kevfev/AutomanPy/
Author: Kevin Feveck
License: GNU GPLv2
Keywords: automan crowdsource quality-assurance
Platform: UNKNOWN
Classifier: Development Status :: 3 - Alpha
Classifier: Programming Language :: Python :: 2.7
Classifier: Programming Language :: Python :: 3.4
Classifier: Programming Language :: Python :: 3.5
Classifier: Programming Language :: Python :: 3.6
Classifier: License :: OSI Approved :: GNU General Public License v2 (GPLv2)
Classifier: Operating System :: OS Independent
Requires-Python: >=2.7.15, !=3.0.*, !=3.1.*, !=3.2.*, !=3.3.*
